assets2036py/__init__.py
assets2036py/assetlogging.py
assets2036py/assetmanager.py
assets2036py/assets.py
assets2036py/communication.py
assets2036py/exceptions.py
assets2036py/py.typed
assets2036py/utilities.py
assets2036py/resources/_endpoint.json
assets2036py/resources/_relations.json
assets2036py/resources/submodel_schema.json
assets2036py-0.1.10.dist-info/LICENSE
assets2036py-0.1.10.dist-info/METADATA
assets2036py-0.1.10.dist-info/NOTICE
assets2036py-0.1.10.dist-info/WHEEL
assets2036py-0.1.10.dist-info/top_level.txt
assets2036py-0.1.10.dist-info/RECORD
