Metadata-Version: 2.1
Name: assets2036py
Version: 0.1.10
Summary: helper library to easily implement assets2036
Home-page: https://github.com/boschresearch/assets2036spy
Author: Daniel Ewert (CR/APT5)
Author-email: Daniel.Ewert@de.bosch.com
License: BIOS
License-File: LICENSE
License-File: NOTICE
Requires-Dist: jsonschema
Requires-Dist: paho-mqtt
Requires-Dist: python-dateutil
